omni_pro_oms/__init__.py
omni_pro_oms/apps.py
omni_pro_oms/mig_settings.py
omni_pro_oms/tests.py
omni_pro_oms/urls.py
omni_pro_oms/admin/__init__.py
omni_pro_oms/admin/config.py
omni_pro_oms/admin/operation.py
omni_pro_oms/admin/operation_type.py
omni_pro_oms/admin/task.py
omni_pro_oms/admin/tenant.py
omni_pro_oms/admin/tenant_operation.py
omni_pro_oms/forms/__init__.py
omni_pro_oms/forms/config.py
omni_pro_oms/forms/operation.py
omni_pro_oms/forms/operation_type.py
omni_pro_oms/forms/task.py
omni_pro_oms/forms/tenant.py
omni_pro_oms/forms/tenant_operation.py
omni_pro_oms/migrations/0001_initial.py
omni_pro_oms/migrations/__init__.py
omni_pro_oms/models/__init__.py
omni_pro_oms/models/config.py
omni_pro_oms/models/operation.py
omni_pro_oms/models/operation_type.py
omni_pro_oms/models/task.py
omni_pro_oms/models/tenant.py
omni_pro_oms/models/tenant_operation.py
omni_pro_oms/serializers/__init__.py
omni_pro_oms/serializers/config.py
omni_pro_oms/serializers/operation.py
omni_pro_oms/serializers/operation_type.py
omni_pro_oms/serializers/task.py
omni_pro_oms/serializers/tenant.py
omni_pro_oms/serializers/tenant_operation.py
omni_pro_oms/views/__init__.py
omni_pro_oms/views/config.py
omni_pro_oms/views/operation.py
omni_pro_oms/views/operation_type.py
omni_pro_oms/views/task.py
omni_pro_oms/views/tenant.py
omni_pro_oms/views/tenant_operation.py
omni_pro_app_oms-0.0.2.dist-info/LICENSE
omni_pro_app_oms-0.0.2.dist-info/METADATA
omni_pro_app_oms-0.0.2.dist-info/WHEEL
omni_pro_app_oms-0.0.2.dist-info/top_level.txt
omni_pro_app_oms-0.0.2.dist-info/RECORD
